pyfunds/__init__.py
pyfunds/either.py
pyfunds/option.py
pyfunds/py.typed
pyfunds/try_.py
pyfunds-1.1.0.dist-info/LICENSE.txt
pyfunds-1.1.0.dist-info/WHEEL
pyfunds-1.1.0.dist-info/METADATA
pyfunds-1.1.0.dist-info/RECORD
